ossit/__init__.py
ossit/api_requestor.py
ossit/config.py
ossit/ossit_response.py
ossit/utils.py
ossit/api_resources/__init__.py
ossit/api_resources/domain.py
ossit/api_resources/statistic.py
ossit-0.2.2.dist-info/LICENSE.txt
ossit-0.2.2.dist-info/METADATA
ossit-0.2.2.dist-info/WHEEL
ossit-0.2.2.dist-info/top_level.txt
ossit-0.2.2.dist-info/RECORD
