Metadata-Version: 2.1
Name: ossit
Version: 0.2.2
Summary: Python Package to connect to ossit API
Author: Wesley Howery
Author-email: wesleyh@stratusadv.com
Classifier: Programming Language :: Python :: 3
Classifier: License :: OSI Approved :: MIT License
Classifier: Operating System :: OS Independent
License-File: LICENSE.txt
